fast_password_validation/__init__.py
fast_password_validation/common-passwords.dat
test/__init__.py
test/settings.py
test/test.py
fast_password_validation-0.1.2.dist-info/METADATA
fast_password_validation-0.1.2.dist-info/WHEEL
fast_password_validation-0.1.2.dist-info/top_level.txt
fast_password_validation-0.1.2.dist-info/RECORD
