Metadata-Version: 2.1
Name: fast-password-validation
Version: 0.1.2
Summary: Drop-in replacement for Django's CommonPasswordValidator with 4x speed and ⅓ memory usage
Home-page: https://git.sr.ht/~kravietz/django-fast-common-passwords-validator
Author: Paweł Krawczyk
Author-email: pawel.krawczyk@hush.com
License: GPLv3
Keywords: django,password,validation
Platform: UNKNOWN
Classifier: Framework :: Django :: 3.0
Classifier: License :: OSI Approved :: GNU General Public License v3 or later (GPLv3+)
Classifier: Programming Language :: Python :: 3
Classifier: Programming Language :: Python :: 3.5
Classifier: Development Status :: 4 - Beta
Classifier: Topic :: Security
Requires-Dist: Django
Requires-Dist: bloom-filter
